learnedbf/__init__.py
learnedbf/complexity_measures.py
learnedbf/BF/__init__.py
learnedbf/classifiers/__init__.py
learnedbf-0.6.2.dist-info/licenses/LICENSE
learnedbf-0.6.2.dist-info/METADATA
learnedbf-0.6.2.dist-info/WHEEL
learnedbf-0.6.2.dist-info/top_level.txt
learnedbf-0.6.2.dist-info/RECORD
